toolsphere/__init__.py
toolsphere/core/__init__.py
toolsphere/core/dsphere.py
toolsphere-0.1.1.dist-info/WHEEL
toolsphere-0.1.1.dist-info/METADATA
toolsphere-0.1.1.dist-info/RECORD
