Metadata-Version: 2.3
Name: toolsphere
Version: 0.1.1
Summary: Add your description here
Author: Yves Augusto
Requires-Dist: configparser
Requires-Dist: connectorx
Requires-Dist: fastexcel
Requires-Dist: hdbcli
Requires-Dist: polars
Requires-Dist: sqlmodel
Requires-Dist: xlsxwriter
Requires-Python: >=3.13
